injinja/__init__.py
injinja/__main__.py
injinja/injinja.py
injinja-1.1.0.dist-info/licenses/LICENSE
injinja-1.1.0.dist-info/WHEEL
injinja-1.1.0.dist-info/entry_points.txt
injinja-1.1.0.dist-info/METADATA
injinja-1.1.0.dist-info/RECORD
