Metadata-Version: 2.4
Name: injinja
Version: 1.1.0
Summary: Injinja: Injectable Jinja Configuration tool. Insanely configurable... config system.
Author: Josh Peak
Author-email: Josh Peak <neozenith.dev@gmail.com>
License-Expression: MIT
License-File: LICENSE
Classifier: Development Status :: 5 - Production/Stable
Classifier: Intended Audience :: Developers
Classifier: Topic :: Software Development :: Build Tools
Classifier: Programming Language :: Python :: 3
Classifier: Programming Language :: Python :: 3.12
Requires-Dist: jinja2
Requires-Dist: pyyaml
Requires-Dist: deepmerge
Requires-Dist: types-pyyaml
Requires-Dist: types-jinja2
Requires-Dist: jsonschema
Requires-Dist: pydantic
Maintainer: Josh Peak
Maintainer-email: Josh Peak <neozenith.dev@gmail.com>
Requires-Python: >=3.12
Project-URL: Changelog, https://github.com/neozenith/injinja/releases
Project-URL: Documentation, https://github.com/neozenith/injinja
Project-URL: Homepage, https://github.com/neozenith/injinja
Project-URL: Issues, https://github.com/neozenith/injinja/issues
Project-URL: Repository, https://github.com/neozenith/injinja.git
